{
  "index_info": {
    "created_at": "2026-01-21T12:03:39.008473",
    "last_updated": "2026-01-21T12:03:39.008473",
    "total_quizzes": 3
  },
  "quizzes": [
    {
      "source_file": "ibm-trivia.json",
      "last_modified": "2026-01-21T11:59:54.089297",
      "file_size": 41800,
      "quiz_title": "IBM公司知识问答",
      "description": "IBM公司知识问答：通过我们包含关于IBM创始人、计算机历史、大型机、个人电脑等问题的IBM公司系列问答，来测试您对这家百年科技巨头的了解程度！",
      "total_questions": 60,
      "questions_per_quiz": 20,
      "actual_questions": 60,
      "added_at": "2026-01-21T12:03:39.056800"
    },
    {
      "source_file": "apple_company.json",
      "last_modified": "2026-01-21T12:00:00.699425",
      "file_size": 39350,
      "quiz_title": "苹果公司知识问答",
      "description": "苹果公司知识问答：通过我们收集的关于史蒂夫·乔布斯、产品历史、Mac、iPhone、iPad等的苹果问答，测试您对这家全球市值最高公司的了解！",
      "total_questions": 60,
      "questions_per_quiz": 20,
      "actual_questions": 60,
      "added_at": "2026-01-21T12:03:39.023730"
    },
    {
      "source_file": "computer_history.json",
      "last_modified": "2026-01-21T11:59:57.631994",
      "file_size": 65978,
      "quiz_title": "计算机历史冷知识测验",
      "description": "包含50+个关于先驱人物、创新技术、里程碑事件和技术发展历程的问题！",
      "total_questions": 100,
      "questions_per_quiz": 20,
      "actual_questions": 100,
      "added_at": "2026-01-21T12:03:39.039285"
    }
  ]
}